[
  {
    "zone_id": "coppito",
    "latitude": 42.3702262,
    "longitude": 13.3267021,
    "fields": [
      {
        "area": 1000,
        "soil_depth": 5,
        "field_id": "coppito_pomodori",
        "soil_moisture_threshold": 70,
        "sensors": [
          { "sensor_id": "sensor1", "type": "soil_moisture", "value": 50, "min_value": 0, "max_value": 100 },
          { "sensor_id": "sensor2", "type": "soil_moisture", "value": 50, "min_value": 0, "max_value": 100 },
          { "sensor_id": "sensor3", "type": "soil_moisture", "value": 50, "min_value": 0, "max_value": 100 },
          { "sensor_id": "sensor4", "type": "soil_moisture", "value": 50, "min_value": 0, "max_value": 100 },
          { "sensor_id": "sensor5", "type": "soil_moisture", "value": 50, "min_value": 0, "max_value": 100 },
          { "sensor_id": "sensor6", "type": "light", "value": 1500, "min_value":0, "max_value": 3000 },
          { "sensor_id": "sensor7", "type": "light", "value": 1500, "min_value":0, "max_value": 3000 },
          { "sensor_id": "sensor8", "type": "light", "value": 1500, "min_value":0, "max_value": 3000 },
          { "sensor_id": "sensor9", "type": "light", "value": 1500, "min_value":0, "max_value": 3000 },
          { "sensor_id": "sensor10", "type": "light", "value": 1500, "min_value":0, "max_value": 3000 },
          { "sensor_id": "sensor11", "type": "humidity", "value": 60, "min_value": 0, "max_value": 100 },
          { "sensor_id": "sensor12", "type": "humidity", "value": 60, "min_value": 0, "max_value": 100 },
          { "sensor_id": "sensor13", "type": "humidity", "value": 60, "min_value": 0, "max_value": 100 },
          { "sensor_id": "sensor14", "type": "humidity", "value": 60, "min_value": 0, "max_value": 100 },
          { "sensor_id": "sensor15", "type": "humidity", "value": 60, "min_value": 0, "max_value": 100 },
          { "sensor_id": "sensor16", "type": "temperature", "value": 20, "min_value": -20, "max_value": 80 },
          { "sensor_id": "sensor17", "type": "temperature", "value": 20, "min_value": -20, "max_value": 80 },
          { "sensor_id": "sensor18", "type": "temperature", "value": 20, "min_value": -20, "max_value": 80 },
          { "sensor_id": "sensor19", "type": "temperature", "value": 20, "min_value": -20, "max_value": 80 },
          { "sensor_id": "sensor20", "type": "temperature", "value": 20, "min_value": -20, "max_value": 80 },
          { "sensor_id": "sensor21", "type": "temperature", "value": 20, "min_value": -20, "max_value": 80 }
        ],
        "actuators": [
          {"actuator_id": "actuator1", "type": "drip_irrigation", "min_value": 0, "max_value": 100, "consumption": 0.4, "measurement": "lpm"},
          {"actuator_id": "actuator2", "type": "drip_irrigation", "min_value": 0, "max_value": 100, "consumption": 0.4, "measurement": "lpm"},
          {"actuator_id": "actuator3", "type": "drip_irrigation", "min_value": 0, "max_value": 100, "consumption": 0.4, "measurement": "lpm"},
          {"actuator_id": "actuator4", "type": "drip_irrigation", "min_value": 0, "max_value": 100, "consumption": 0.4, "measurement": "lpm"},
          {"actuator_id": "actuator5", "type": "sprinkler", "min_value": 0, "max_value": 100, "consumption": 0.4, "measurement": "lpm"},
          {"actuator_id": "actuator1", "type": "sprinkler", "min_value": 0, "max_value": 100, "consumption": 0.4, "measurement": "lpm"},
          {"actuator_id": "actuator2", "type": "sprinkler", "min_value": 0, "max_value": 100, "consumption": 0.4, "measurement": "lpm"},
          {"actuator_id": "actuator3", "type": "sprinkler", "min_value": 0, "max_value": 100, "consumption": 0.4, "measurement": "lpm"},
          {"actuator_id": "actuator4", "type": "sprinkler", "min_value": 0, "max_value": 100, "consumption": 0.4, "measurement": "lpm"},
          {"actuator_id": "actuator5", "type": "sprinkler", "min_value": 0, "max_value": 100, "consumption": 0.4, "measurement": "lpm"}
        ]
      },
      {
        "area": 1000,
        "soil_depth": 5,
        "field_id": "coppito_zucchine",
        "soil_moisture_threshold": 65,
        "sensors": [
          { "sensor_id": "sensor22", "type": "soil_moisture", "value": 50, "min_value": 0, "max_value": 100 },
          { "sensor_id": "sensor23", "type": "soil_moisture", "value": 50, "min_value": 0, "max_value": 100 },
          { "sensor_id": "sensor24", "type": "soil_moisture", "value": 50, "min_value": 0, "max_value": 100 },
          { "sensor_id": "sensor25", "type": "soil_moisture", "value": 50, "min_value": 0, "max_value": 100 },
          { "sensor_id": "sensor26", "type": "soil_moisture", "value": 50, "min_value": 0, "max_value": 100 },
          { "sensor_id": "sensor27", "type": "light", "value": 1500, "min_value":0, "max_value": 3000 },
          { "sensor_id": "sensor28", "type": "light", "value": 1500, "min_value":0, "max_value": 3000 },
          { "sensor_id": "sensor29", "type": "light", "value": 1500, "min_value":0, "max_value": 3000 },
          { "sensor_id": "sensor30", "type": "light", "value": 1500, "min_value":0, "max_value": 3000 },
          { "sensor_id": "sensor31", "type": "light", "value": 1500, "min_value":0, "max_value": 3000 },
          { "sensor_id": "sensor32", "type": "humidity", "value": 60, "min_value": 0, "max_value": 100 },
          { "sensor_id": "sensor33", "type": "humidity", "value": 60, "min_value": 0, "max_value": 100 },
          { "sensor_id": "sensor34", "type": "humidity", "value": 60, "min_value": 0, "max_value": 100 },
          { "sensor_id": "sensor35", "type": "humidity", "value": 60, "min_value": 0, "max_value": 100 },
          { "sensor_id": "sensor36", "type": "humidity", "value": 60, "min_value": 0, "max_value": 100 },
          { "sensor_id": "sensor37", "type": "temperature", "value": 20, "min_value": -20, "max_value": 80 },
          { "sensor_id": "sensor38", "type": "temperature", "value": 20, "min_value": -20, "max_value": 80 },
          { "sensor_id": "sensor39", "type": "temperature", "value": 20, "min_value": -20, "max_value": 80 },
          { "sensor_id": "sensor40", "type": "temperature", "value": 20, "min_value": -20, "max_value": 80 },
          { "sensor_id": "sensor41", "type": "temperature", "value": 20, "min_value": -20, "max_value": 80 },
          { "sensor_id": "sensor42", "type": "temperature", "value": 20, "min_value": -20, "max_value": 80 }
        ],
        "actuators": [
          {"actuator_id": "actuator6", "type": "drip_irrigation", "min_value": 0, "max_value": 100, "consumption": 0.4, "measurement": "lpm"},
          {"actuator_id": "actuator7", "type": "drip_irrigation", "min_value": 0, "max_value": 100, "consumption": 0.4, "measurement": "lpm"},
          {"actuator_id": "actuator8", "type": "drip_irrigation", "min_value": 0, "max_value": 100, "consumption": 0.4, "measurement": "lpm"},
          {"actuator_id": "actuator9", "type": "drip_irrigation", "min_value": 0, "max_value": 100, "consumption": 0.4, "measurement": "lpm"},
          {"actuator_id": "actuator10", "type": "sprinkler", "min_value": 0, "max_value": 100, "consumption": 0.4, "measurement": "lpm"},
          {"actuator_id": "actuator11", "type": "sprinkler", "min_value": 0, "max_value": 100, "consumption": 0.4, "measurement": "lpm"},
          {"actuator_id": "actuator12", "type": "sprinkler", "min_value": 0, "max_value": 100, "consumption": 0.4, "measurement": "lpm"},
          {"actuator_id": "actuator13", "type": "sprinkler", "min_value": 0, "max_value": 100, "consumption": 0.4, "measurement": "lpm"},
          {"actuator_id": "actuator14", "type": "sprinkler", "min_value": 0, "max_value": 100, "consumption": 0.4, "measurement": "lpm"},
          {"actuator_id": "actuator15", "type": "sprinkler", "min_value": 0, "max_value": 100, "consumption": 0.4, "measurement": "lpm"}
        ]
      },
      {
        "area": 1000,
        "soil_depth": 5,
        "field_id": "coppito_peperoni",
        "soil_moisture_threshold": 55,
        "sensors": [
          { "sensor_id": "sensor43", "type": "soil_moisture", "value": 50, "min_value": 0, "max_value": 100 },
          { "sensor_id": "sensor44", "type": "soil_moisture", "value": 50, "min_value": 0, "max_value": 100 },
          { "sensor_id": "sensor45", "type": "soil_moisture", "value": 50, "min_value": 0, "max_value": 100 },
          { "sensor_id": "sensor46", "type": "soil_moisture", "value": 50, "min_value": 0, "max_value": 100 },
          { "sensor_id": "sensor47", "type": "soil_moisture", "value": 50, "min_value": 0, "max_value": 100 },
          { "sensor_id": "sensor48", "type": "light", "value": 1500, "min_value":0, "max_value": 3000 },
          { "sensor_id": "sensor49", "type": "light", "value": 1500, "min_value":0, "max_value": 3000 },
          { "sensor_id": "sensor50", "type": "light", "value": 1500, "min_value":0, "max_value": 3000 },
          { "sensor_id": "sensor51", "type": "light", "value": 1500, "min_value":0, "max_value": 3000 },
          { "sensor_id": "sensor52", "type": "light", "value": 1500, "min_value":0, "max_value": 3000 },
          { "sensor_id": "sensor53", "type": "humidity", "value": 60, "min_value": 0, "max_value": 100 },
          { "sensor_id": "sensor54", "type": "humidity", "value": 60, "min_value": 0, "max_value": 100 },
          { "sensor_id": "sensor55", "type": "humidity", "value": 60, "min_value": 0, "max_value": 100 },
          { "sensor_id": "sensor56", "type": "humidity", "value": 60, "min_value": 0, "max_value": 100 },
          { "sensor_id": "sensor57", "type": "humidity", "value": 60, "min_value": 0, "max_value": 100 },
          { "sensor_id": "sensor58", "type": "temperature", "value": 20, "min_value": -20, "max_value": 80 },
          { "sensor_id": "sensor59", "type": "temperature", "value": 20, "min_value": -20, "max_value": 80 },
          { "sensor_id": "sensor60", "type": "temperature", "value": 20, "min_value": -20, "max_value": 80 },
          { "sensor_id": "sensor61", "type": "temperature", "value": 20, "min_value": -20, "max_value": 80 },
          { "sensor_id": "sensor62", "type": "temperature", "value": 20, "min_value": -20, "max_value": 80 },
          { "sensor_id": "sensor63", "type": "temperature", "value": 20, "min_value": -20, "max_value": 80 }
        ],
        "actuators": [
          {"actuator_id": "actuator16", "type": "drip_irrigation", "min_value": 0, "max_value": 100, "consumption": 0.4, "measurement": "lpm"},
          {"actuator_id": "actuator17", "type": "drip_irrigation", "min_value": 0, "max_value": 100, "consumption": 0.4, "measurement": "lpm"},
          {"actuator_id": "actuator18", "type": "drip_irrigation", "min_value": 0, "max_value": 100, "consumption": 0.4, "measurement": "lpm"},
          {"actuator_id": "actuator19", "type": "drip_irrigation", "min_value": 0, "max_value": 100, "consumption": 0.4, "measurement": "lpm"},
          {"actuator_id": "actuator20", "type": "sprinkler", "min_value": 0, "max_value": 100, "consumption": 0.4, "measurement": "lpm"},
          {"actuator_id": "actuator21", "type": "sprinkler", "min_value": 0, "max_value": 100, "consumption": 0.4, "measurement": "lpm"},
          {"actuator_id": "actuator22", "type": "sprinkler", "min_value": 0, "max_value": 100, "consumption": 0.4, "measurement": "lpm"},
          {"actuator_id": "actuator23", "type": "sprinkler", "min_value": 0, "max_value": 100, "consumption": 0.4, "measurement": "lpm"},
          {"actuator_id": "actuator24", "type": "sprinkler", "min_value": 0, "max_value": 100, "consumption": 0.4, "measurement": "lpm"},
          {"actuator_id": "actuator25", "type": "sprinkler", "min_value": 0, "max_value": 100, "consumption": 0.4, "measurement": "lpm"}
        ]
      }
    ]
  },
  {
    "zone_id": "collebrincioni",
    "latitude": 42.4037844,
    "longitude": 13.4275238,
    "soil_moisture_threshold": 50,
    "fields": [
      {
        "area": 1000,
        "soil_depth": 5,
        "field_id": "collebrincioni_pomodori",
        "soil_moisture_threshold": 70,
        "sensors": [
          { "sensor_id": "sensor64", "type": "soil_moisture", "value": 50, "min_value": 0, "max_value": 100 },
          { "sensor_id": "sensor65", "type": "soil_moisture", "value": 50, "min_value": 0, "max_value": 100 },
          { "sensor_id": "sensor66", "type": "soil_moisture", "value": 50, "min_value": 0, "max_value": 100 },
          { "sensor_id": "sensor67", "type": "soil_moisture", "value": 50, "min_value": 0, "max_value": 100 },
          { "sensor_id": "sensor68", "type": "soil_moisture", "value": 50, "min_value": 0, "max_value": 100 },
          { "sensor_id": "sensor69", "type": "light", "value": 1500, "min_value":0, "max_value": 3000 },
          { "sensor_id": "sensor70", "type": "light", "value": 1500, "min_value":0, "max_value": 3000 },
          { "sensor_id": "sensor71", "type": "light", "value": 1500, "min_value":0, "max_value": 3000 },
          { "sensor_id": "sensor72", "type": "light", "value": 1500, "min_value":0, "max_value": 3000 },
          { "sensor_id": "sensor73", "type": "light", "value": 1500, "min_value":0, "max_value": 3000 },
          { "sensor_id": "sensor74", "type": "humidity", "value": 60, "min_value": 0, "max_value": 100 },
          { "sensor_id": "sensor75", "type": "humidity", "value": 60, "min_value": 0, "max_value": 100 },
          { "sensor_id": "sensor76", "type": "humidity", "value": 60, "min_value": 0, "max_value": 100 },
          { "sensor_id": "sensor77", "type": "humidity", "value": 60, "min_value": 0, "max_value": 100 },
          { "sensor_id": "sensor78", "type": "humidity", "value": 60, "min_value": 0, "max_value": 100 },
          { "sensor_id": "sensor79", "type": "temperature", "value": 20, "min_value": -20, "max_value": 80 },
          { "sensor_id": "sensor80", "type": "temperature", "value": 20, "min_value": -20, "max_value": 80 },
          { "sensor_id": "sensor81", "type": "temperature", "value": 20, "min_value": -20, "max_value": 80 },
          { "sensor_id": "sensor82", "type": "temperature", "value": 20, "min_value": -20, "max_value": 80 },
          { "sensor_id": "sensor83", "type": "temperature", "value": 20, "min_value": -20, "max_value": 80 },
          { "sensor_id": "sensor84", "type": "temperature", "value": 20, "min_value": -20, "max_value": 80 }
        ],
        "actuators": [
          {"actuator_id": "actuator26", "type": "drip_irrigation", "min_value": 0, "max_value": 100, "consumption": 0.4, "measurement": "lpm"},
          {"actuator_id": "actuator27", "type": "drip_irrigation", "min_value": 0, "max_value": 100, "consumption": 0.4, "measurement": "lpm"},
          {"actuator_id": "actuator28", "type": "drip_irrigation", "min_value": 0, "max_value": 100, "consumption": 0.4, "measurement": "lpm"},
          {"actuator_id": "actuator29", "type": "drip_irrigation", "min_value": 0, "max_value": 100, "consumption": 0.4, "measurement": "lpm"},
          {"actuator_id": "actuator30", "type": "sprinkler", "min_value": 0, "max_value": 100, "consumption": 0.4, "measurement": "lpm"},
          {"actuator_id": "actuator31", "type": "sprinkler", "min_value": 0, "max_value": 100, "consumption": 0.4, "measurement": "lpm"},
          {"actuator_id": "actuator32", "type": "sprinkler", "min_value": 0, "max_value": 100, "consumption": 0.4, "measurement": "lpm"},
          {"actuator_id": "actuator33", "type": "sprinkler", "min_value": 0, "max_value": 100, "consumption": 0.4, "measurement": "lpm"},
          {"actuator_id": "actuator34", "type": "sprinkler", "min_value": 0, "max_value": 100, "consumption": 0.4, "measurement": "lpm"},
          {"actuator_id": "actuator35", "type": "sprinkler", "min_value": 0, "max_value": 100, "consumption": 0.4, "measurement": "lpm"}
        ]
      },
      {
        "area": 1000,
        "soil_depth": 5,
        "field_id": "collebrincioni_zucchine",
        "soil_moisture_threshold": 65,
        "sensors": [
          { "sensor_id": "sensor85", "type": "soil_moisture", "value": 50, "min_value": 0, "max_value": 100 },
          { "sensor_id": "sensor86", "type": "soil_moisture", "value": 50, "min_value": 0, "max_value": 100 },
          { "sensor_id": "sensor87", "type": "soil_moisture", "value": 50, "min_value": 0, "max_value": 100 },
          { "sensor_id": "sensor88", "type": "soil_moisture", "value": 50, "min_value": 0, "max_value": 100 },
          { "sensor_id": "sensor89", "type": "soil_moisture", "value": 50, "min_value": 0, "max_value": 100 },
          { "sensor_id": "sensor90", "type": "light", "value": 1500, "min_value":0, "max_value": 3000 },
          { "sensor_id": "sensor91", "type": "light", "value": 1500, "min_value":0, "max_value": 3000 },
          { "sensor_id": "sensor92", "type": "light", "value": 1500, "min_value":0, "max_value": 3000 },
          { "sensor_id": "sensor93", "type": "light", "value": 1500, "min_value":0, "max_value": 3000 },
          { "sensor_id": "sensor94", "type": "light", "value": 1500, "min_value":0, "max_value": 3000 },
          { "sensor_id": "sensor95", "type": "humidity", "value": 60, "min_value": 0, "max_value": 100 },
          { "sensor_id": "sensor96", "type": "humidity", "value": 60, "min_value": 0, "max_value": 100 },
          { "sensor_id": "sensor97", "type": "humidity", "value": 60, "min_value": 0, "max_value": 100 },
          { "sensor_id": "sensor98", "type": "humidity", "value": 60, "min_value": 0, "max_value": 100 },
          { "sensor_id": "sensor99", "type": "humidity", "value": 60, "min_value": 0, "max_value": 100 },
          { "sensor_id": "sensor100", "type": "temperature", "value": 20, "min_value": -20, "max_value": 80 },
          { "sensor_id": "sensor101", "type": "temperature", "value": 20, "min_value": -20, "max_value": 80 },
          { "sensor_id": "sensor102", "type": "temperature", "value": 20, "min_value": -20, "max_value": 80 },
          { "sensor_id": "sensor103", "type": "temperature", "value": 20, "min_value": -20, "max_value": 80 },
          { "sensor_id": "sensor104", "type": "temperature", "value": 20, "min_value": -20, "max_value": 80 },
          { "sensor_id": "sensor105", "type": "temperature", "value": 20, "min_value": -20, "max_value": 80 }
        ],
        "actuators": [
          {"actuator_id": "actuator36", "type": "drip_irrigation", "min_value": 0, "max_value": 100, "consumption": 0.4, "measurement": "lpm"},
          {"actuator_id": "actuator37", "type": "drip_irrigation", "min_value": 0, "max_value": 100, "consumption": 0.4, "measurement": "lpm"},
          {"actuator_id": "actuator38", "type": "drip_irrigation", "min_value": 0, "max_value": 100, "consumption": 0.4, "measurement": "lpm"},
          {"actuator_id": "actuator39", "type": "drip_irrigation", "min_value": 0, "max_value": 100, "consumption": 0.4, "measurement": "lpm"},
          {"actuator_id": "actuator40", "type": "sprinkler", "min_value": 0, "max_value": 100, "consumption": 0.4, "measurement": "lpm"},
          {"actuator_id": "actuator41", "type": "sprinkler", "min_value": 0, "max_value": 100, "consumption": 0.4, "measurement": "lpm"},
          {"actuator_id": "actuator42", "type": "sprinkler", "min_value": 0, "max_value": 100, "consumption": 0.4, "measurement": "lpm"},
          {"actuator_id": "actuator43", "type": "sprinkler", "min_value": 0, "max_value": 100, "consumption": 0.4, "measurement": "lpm"},
          {"actuator_id": "actuator44", "type": "sprinkler", "min_value": 0, "max_value": 100, "consumption": 0.4, "measurement": "lpm"},
          {"actuator_id": "actuator45", "type": "sprinkler", "min_value": 0, "max_value": 100, "consumption": 0.4, "measurement": "lpm"}
        ]
      },
      {
        "area": 1000,
        "soil_depth": 5,
        "field_id": "collebrincioni_peperoni",
        "soil_moisture_threshold": 55,
        "sensors": [
          { "sensor_id": "sensor106", "type": "soil_moisture", "value": 50, "min_value": 0, "max_value": 100 },
          { "sensor_id": "sensor107", "type": "soil_moisture", "value": 50, "min_value": 0, "max_value": 100 },
          { "sensor_id": "sensor108", "type": "soil_moisture", "value": 50, "min_value": 0, "max_value": 100 },
          { "sensor_id": "sensor109", "type": "soil_moisture", "value": 50, "min_value": 0, "max_value": 100 },
          { "sensor_id": "sensor110", "type": "soil_moisture", "value": 50, "min_value": 0, "max_value": 100 },
          { "sensor_id": "sensor111", "type": "light", "value": 1500, "min_value":0, "max_value": 3000 },
          { "sensor_id": "sensor112", "type": "light", "value": 1500, "min_value":0, "max_value": 3000 },
          { "sensor_id": "sensor113", "type": "light", "value": 1500, "min_value":0, "max_value": 3000 },
          { "sensor_id": "sensor114", "type": "light", "value": 1500, "min_value":0, "max_value": 3000 },
          { "sensor_id": "sensor115", "type": "light", "value": 1500, "min_value":0, "max_value": 3000 },
          { "sensor_id": "sensor116", "type": "humidity", "value": 60, "min_value": 0, "max_value": 100 },
          { "sensor_id": "sensor117", "type": "humidity", "value": 60, "min_value": 0, "max_value": 100 },
          { "sensor_id": "sensor118", "type": "humidity", "value": 60, "min_value": 0, "max_value": 100 },
          { "sensor_id": "sensor119", "type": "humidity", "value": 60, "min_value": 0, "max_value": 100 },
          { "sensor_id": "sensor120", "type": "humidity", "value": 60, "min_value": 0, "max_value": 100 },
          { "sensor_id": "sensor121", "type": "temperature", "value": 20, "min_value": -20, "max_value": 80 },
          { "sensor_id": "sensor122", "type": "temperature", "value": 20, "min_value": -20, "max_value": 80 },
          { "sensor_id": "sensor123", "type": "temperature", "value": 20, "min_value": -20, "max_value": 80 },
          { "sensor_id": "sensor124", "type": "temperature", "value": 20, "min_value": -20, "max_value": 80 },
          { "sensor_id": "sensor125", "type": "temperature", "value": 20, "min_value": -20, "max_value": 80 },
          { "sensor_id": "sensor126", "type": "temperature", "value": 20, "min_value": -20, "max_value": 80 }
        ],
        "actuators": [
          {"actuator_id": "actuator46", "type": "drip_irrigation", "min_value": 0, "max_value": 100, "consumption": 0.4, "measurement": "lpm"},
          {"actuator_id": "actuator47", "type": "drip_irrigation", "min_value": 0, "max_value": 100, "consumption": 0.4, "measurement": "lpm"},
          {"actuator_id": "actuator48", "type": "drip_irrigation", "min_value": 0, "max_value": 100, "consumption": 0.4, "measurement": "lpm"},
          {"actuator_id": "actuator49", "type": "drip_irrigation", "min_value": 0, "max_value": 100, "consumption": 0.4, "measurement": "lpm"},
          {"actuator_id": "actuator50", "type": "sprinkler", "min_value": 0, "max_value": 100, "consumption": 0.4, "measurement": "lpm"},
          {"actuator_id": "actuator51", "type": "sprinkler", "min_value": 0, "max_value": 100, "consumption": 0.4, "measurement": "lpm"},
          {"actuator_id": "actuator52", "type": "sprinkler", "min_value": 0, "max_value": 100, "consumption": 0.4, "measurement": "lpm"},
          {"actuator_id": "actuator53", "type": "sprinkler", "min_value": 0, "max_value": 100, "consumption": 0.4, "measurement": "lpm"},
          {"actuator_id": "actuator54", "type": "sprinkler", "min_value": 0, "max_value": 100, "consumption": 0.4, "measurement": "lpm"},
          {"actuator_id": "actuator55", "type": "sprinkler", "min_value": 0, "max_value": 100, "consumption": 0.4, "measurement": "lpm"}
        ]
      }
    ]
  }
]
